setup.py
sfxcentralconfig/__init__.py
sfxcentralconfig/operations.py
sfxcentralconfig.egg-info/PKG-INFO
sfxcentralconfig.egg-info/SOURCES.txt
sfxcentralconfig.egg-info/dependency_links.txt
sfxcentralconfig.egg-info/not-zip-safe
sfxcentralconfig.egg-info/top_level.txt