Metadata-Version: 1.0
Name: sfxcentralconfig
Version: 0.3
Summary: operation and library
Home-page: UNKNOWN
Author: UNKNOWN
Author-email: vardhinenimanoj4@gmail.com
License: UNKNOWN
Platform: UNKNOWN
